images_into_array/images_into_array.py
images_into_array-2.0.7.dist-info/LICENSE
images_into_array-2.0.7.dist-info/METADATA
images_into_array-2.0.7.dist-info/WHEEL
images_into_array-2.0.7.dist-info/top_level.txt
images_into_array-2.0.7.dist-info/RECORD
